MANIFEST.in
hanqingcode.py
rose.txt
setup.py
hanqingcode.egg-info/PKG-INFO
hanqingcode.egg-info/SOURCES.txt
hanqingcode.egg-info/dependency_links.txt
hanqingcode.egg-info/entry_points.txt
hanqingcode.egg-info/top_level.txt