Metadata-Version: 1.0
Name: hanqingcode
Version: 1.1.8
Summary: this is a gift for someone!
Home-page: https://pypi.org/project/hangqincode
Author: hdy
Author-email: 1015296415@qq.com
License: MIT
Platform: UNKNOWN
